resources/endpoints.v1.json
resources/template_red_sailfish.json
sheetcloud/__init__.py
sheetcloud/conn.py
sheetcloud/drive.py
sheetcloud/env.py
sheetcloud/fun.py
sheetcloud/orm.py
sheetcloud/sheets.py
sheetcloud/templates.py
sheetcloud/user.py
sheetcloud/utils.py
tests/test_conn.py
tests/test_orm.py
sheetcloud-0.1.0.post12.dist-info/LICENSE
sheetcloud-0.1.0.post12.dist-info/METADATA
sheetcloud-0.1.0.post12.dist-info/WHEEL
sheetcloud-0.1.0.post12.dist-info/top_level.txt
sheetcloud-0.1.0.post12.dist-info/RECORD
