Metadata-Version: 2.1
Name: sheetcloud
Version: 0.1.0.post12
Summary: Sheetcloud.de | Turn Spreadsheets into a Cloud Database | Account required
Author-email: "sheetcloud.org" <contact@sheetcloud.org>
Project-URL: Homepage, https://www.sheetcloud.org
Project-URL: Tracker, https://github.com/sheetcloud/sheetcloud/issues
Project-URL: Source, https://github.com/sheetcloud/sheetcloud
Project-URL: Examples, https://github.com/sheetcloud
Keywords: Spreadsheets,RAD,Database,Cloud
Classifier: Development Status :: 3 - Alpha
Classifier: Intended Audience :: Developers
Classifier: Topic :: Database
Classifier: Topic :: Office/Business :: Financial :: Spreadsheet
Classifier: Programming Language :: Python :: 3
Classifier: License :: OSI Approved :: MIT License
Classifier: Operating System :: OS Independent
Requires-Python: >=3.7
License-File: LICENSE
Requires-Dist: pandas (>=1.2.5)
Requires-Dist: pyarrow (>=11.0.0)
Requires-Dist: requests (>=2.28.2)
